_TFL/Abbr_Key_Dict.py
_TFL/Accessor.py
_TFL/Alias_Dict.py
_TFL/Angle.py
_TFL/App_State.py
_TFL/App_Test.py
_TFL/Apply_All.py
_TFL/Ascii.py
_TFL/Attr_Mapper.py
_TFL/B64.py
_TFL/Babel.py
_TFL/Black_Hole.py
_TFL/CAO.py
_TFL/Caller.py
_TFL/Color.py
_TFL/Command.py
_TFL/Compass_Rose.py
_TFL/Composition.py
_TFL/Context.py
_TFL/Currency.py
_TFL/DL_List.py
_TFL/Date_Time.py
_TFL/Decorator.py
_TFL/Dingbats.py
_TFL/Divisor_Dag.py
_TFL/EU_Currency.py
_TFL/Environment.py
_TFL/Error.py
_TFL/Extreme_Value_Counter.py
_TFL/FCM.py
_TFL/FN_Matcher.py
_TFL/FO.py
_TFL/Field_Reader.py
_TFL/Filename.py
_TFL/Filter.py
_TFL/Function.py
_TFL/Functor.py
_TFL/G8R.py
_TFL/Gauge_Logger.py
_TFL/Generators.py
_TFL/HTML.py
_TFL/I18N.py
_TFL/IV_Number.py
_TFL/Infinity.py
_TFL/Int_Partition.py
_TFL/Interval_Set.py
_TFL/Ival_Map.py
_TFL/LICENSE
_TFL/Logger.py
_TFL/Math_Func.py
_TFL/Module.py
_TFL/NO_List.py
_TFL/Numeric_Interval.py
_TFL/Observed_Value.py
_TFL/Ordered_Set.py
_TFL/Output.py
_TFL/PMPP.py
_TFL/Package_Namespace.py
_TFL/Parameters.py
_TFL/Password_Hasher.py
_TFL/Primes.py
_TFL/Product_Version.py
_TFL/Proxy.py
_TFL/Py2C_Wrapper.py
_TFL/Py_Interpreter.py
_TFL/Q_Exp.py
_TFL/Q_Exp_CAO.py
_TFL/Q_Result.py
_TFL/README.rst
_TFL/RFC2822_date.py
_TFL/Range.py
_TFL/Ratio.py
_TFL/Re_Filter.py
_TFL/Record.py
_TFL/Recordifier.py
_TFL/Regexp.py
_TFL/SMTP.py
_TFL/Script.py
_TFL/Search_Path.py
_TFL/Secure_Hash.py
_TFL/Sorted_By.py
_TFL/Sphere.py
_TFL/Text_Translation_Cacher.py
_TFL/Ticker.py
_TFL/Timeline.py
_TFL/Traceback_Printer.py
_TFL/Trie.py
_TFL/UCD.py
_TFL/Undef.py
_TFL/Url.py
_TFL/User_Config.py
_TFL/VERSION.py
_TFL/_UCD_map.py
_TFL/__init__.py
_TFL/_pyk3.py
_TFL/babel.cfg
_TFL/bayesian.py
_TFL/binary_string.py
_TFL/d_dict.py
_TFL/dc_base32.py
_TFL/defaultdict.py
_TFL/display.py
_TFL/formatted_repr.py
_TFL/fs_find.py
_TFL/json_dump.py
_TFL/load_config_file.py
_TFL/module_copy.py
_TFL/multimap.py
_TFL/normalized_indent.py
_TFL/object_globals.py
_TFL/open_w_lock.py
_TFL/package_imports.py
TFL-3.9.dist-info/LICENSE
TFL-3.9.dist-info/METADATA
TFL-3.9.dist-info/WHEEL
TFL-3.9.dist-info/top_level.txt
TFL-3.9.dist-info/RECORD
